{"stats":{"minecraft:killed_by":{"minecraft:wolf":1,"minecraft:wither_skeleton":7,"minecraft:spider":4,"minecraft:vindicator":3},"minecraft:custom":{"minecraft:interact_with_anvil":4,"minecraft:mob_kills":101,"minecraft:interact_with_crafting_table":44,"minecraft:open_shulker_box":6,"minecraft:leave_game":25,"minecraft:time_since_death":71964,"minecraft:sprint_one_cm":991286,"minecraft:walk_one_cm":863398,"minecraft:drop":72,"minecraft:play_time":1030793,"minecraft:deaths":16,"minecraft:sneak_time":57888,"minecraft:walk_under_water_one_cm":164,"minecraft:jump":7860,"minecraft:walk_on_water_one_cm":2134,"minecraft:total_world_time":1325237,"minecraft:time_since_rest":71965,"minecraft:damage_taken":4440,"minecraft:open_enderchest":9,"minecraft:damage_dealt":29183,"minecraft:fly_one_cm":3287328,"minecraft:crouch_one_cm":59479,"minecraft:fall_one_cm":24538},"minecraft:dropped":{"minecraft:yellow_concrete":1,"minecraft:smooth_quartz_stairs":2,"minecraft:purple_concrete":2,"minecraft:command_block":2,"minecraft:yellow_carpet":2,"minecraft:gray_concrete":5,"minecraft:repeater":1,"minecraft:wooden_axe":11,"minecraft:white_concrete":1,"minecraft:smooth_quartz":2,"minecraft:smooth_quartz_slab":2,"minecraft:black_concrete":2,"minecraft:white_wool":1,"minecraft:redstone":1,"minecraft:pink_concrete":1,"minecraft:red_concrete":2,"minecraft:lime_concrete":1,"minecraft:netherite_sword":11,"minecraft:orange_concrete":1,"minecraft:blue_concrete":2,"minecraft:comparator":1,"minecraft:structure_block":1,"minecraft:green_concrete":2,"minecraft:light_gray_concrete":2,"minecraft:debug_stick":2,"minecraft:magenta_concrete":1,"minecraft:light_blue_concrete":1,"minecraft:oak_sign":1,"minecraft:light":1,"minecraft:cyan_concrete":2,"minecraft:written_book":2,"minecraft:black_wool":1,"minecraft:brown_concrete":2},"minecraft:killed":{"minecraft:witch":15,"minecraft:vindicator":16,"minecraft:spider":30,"minecraft:wolf":11,"minecraft:creeper":16,"minecraft:wither_skeleton":13},"minecraft:crafted":{"minecraft:wolf_spawn_egg":1,"minecraft:totem_of_undying":1},"minecraft:picked_up":{"minecraft:wooden_axe":21,"minecraft:black_carpet":4,"minecraft:light_blue_concrete":1,"minecraft:ender_chest":11,"minecraft:structure_block":1,"minecraft:potion":2,"minecraft:light":1,"minecraft:blue_concrete":2,"minecraft:polished_deepslate":1,"minecraft:string":48,"minecraft:orange_concrete":1,"minecraft:item_frame":7,"minecraft:oak_sign":12,"minecraft:comparator":1,"minecraft:netherite_sword":21,"minecraft:written_book":3,"minecraft:smooth_quartz":2,"minecraft:smooth_quartz_stairs":2,"minecraft:stick":2,"minecraft:crimson_button":1,"minecraft:stone_button":3,"minecraft:redstone":12,"minecraft:command_block":13,"minecraft:white_shulker_box":1,"minecraft:white_wool":1,"minecraft:repeater":2,"minecraft:glow_ink_sac":11,"minecraft:filled_map":6,"minecraft:brown_concrete":2,"minecraft:waxed_copper_block":1,"minecraft:gunpowder":21,"minecraft:gray_concrete":5,"minecraft:bone":20,"minecraft:glowstone_dust":3,"minecraft:glass_bottle":5,"minecraft:cyan_concrete":2,"minecraft:purple_concrete":2,"minecraft:debug_stick":13,"minecraft:pink_concrete":1,"minecraft:yellow_concrete":1,"minecraft:lime_concrete":1,"minecraft:spider_eye":23,"minecraft:light_gray_concrete":2,"minecraft:sugar":3,"minecraft:yellow_carpet":17,"minecraft:green_concrete":2,"minecraft:black_concrete":2,"minecraft:lever":21,"minecraft:polished_blackstone_button":27,"minecraft:white_concrete":1,"minecraft:emerald":11,"minecraft:oak_button":1,"minecraft:magenta_concrete":1,"minecraft:black_wool":1,"minecraft:red_concrete":2,"minecraft:coal":7,"minecraft:smooth_quartz_slab":2},"minecraft:used":{"minecraft:oak_fence":4,"minecraft:trident":21,"minecraft:netherite_sword":318,"minecraft:polished_deepslate":15,"minecraft:orange_concrete":2,"minecraft:smooth_quartz_slab":18,"minecraft:red_concrete":25,"minecraft:redstone":123,"minecraft:carrot_on_a_stick":92,"minecraft:oak_sign":79,"minecraft:black_carpet":8,"minecraft:tinted_glass":44,"minecraft:ender_chest":11,"minecraft:brown_concrete":1,"minecraft:purple_shulker_box":1,"minecraft:white_shulker_box":2,"minecraft:structure_block":19,"minecraft:debug_stick":146,"minecraft:anvil":5,"minecraft:yellow_carpet":62,"minecraft:blue_concrete":1,"minecraft:polished_deepslate_stairs":7,"minecraft:glass":6,"minecraft:wooden_axe":8,"minecraft:crimson_button":4,"minecraft:sea_lantern":22,"minecraft:grass_block":33,"minecraft:light_weighted_pressure_plate":3,"minecraft:smooth_quartz":6,"minecraft:diorite_wall":10,"minecraft:item_frame":43,"minecraft:purple_concrete":1,"minecraft:repeater":39,"minecraft:redstone_lamp":17,"minecraft:lime_concrete":1,"minecraft:hay_block":35,"minecraft:written_book":5,"minecraft:iron_trapdoor":116,"minecraft:wolf_spawn_egg":1,"minecraft:deepslate_tile_stairs":5,"minecraft:stone_pressure_plate":12,"minecraft:cooked_beef":5,"minecraft:calcite":55,"minecraft:water_bucket":1,"minecraft:powered_rail":1,"minecraft:redstone_block":3,"minecraft:structure_void":14,"minecraft:glow_ink_sac":1,"minecraft:waxed_copper_block":7,"minecraft:smooth_quartz_stairs":70,"minecraft:white_wool":7,"minecraft:pink_concrete":1,"minecraft:comparator":30,"minecraft:stripped_dark_oak_log":49,"minecraft:yellow_terracotta":1163,"minecraft:light_blue_concrete":1,"minecraft:crafting_table":2,"minecraft:yellow_concrete":145,"minecraft:gray_concrete":3909,"minecraft:redstone_torch":5,"minecraft:sticky_piston":4,"minecraft:piston":3,"minecraft:lever":120,"minecraft:green_concrete":1,"minecraft:light":115,"minecraft:black_wool":16,"minecraft:black_concrete":168,"minecraft:command_block":226,"minecraft:light_gray_concrete":106,"minecraft:oak_button":16,"minecraft:barrier":37,"minecraft:map":5,"minecraft:stone_button":27,"minecraft:cyan_concrete":1,"minecraft:magenta_concrete":1,"minecraft:polished_granite":6,"minecraft:dark_oak_fence":3,"minecraft:chain_command_block":118,"minecraft:glass_pane":12,"minecraft:repeating_command_block":32,"minecraft:polished_blackstone_button":22,"minecraft:white_concrete":225,"minecraft:warped_button":1,"minecraft:gray_stained_glass":41}},"DataVersion":3120}